LICENSE
MANIFEST.in
README.rst
setup.cfg
setup.py
logilab_sphinx_themes/__init__.py
logilab_sphinx_themes/__init__.pyc
logilab_sphinx_themes/_version.py
logilab_sphinx_themes/_version.pyc
logilab_sphinx_themes/layout.html
logilab_sphinx_themes/theme.conf
logilab_sphinx_themes.egg-info/PKG-INFO
logilab_sphinx_themes.egg-info/SOURCES.txt
logilab_sphinx_themes.egg-info/dependency_links.txt
logilab_sphinx_themes.egg-info/entry_points.txt
logilab_sphinx_themes.egg-info/requires.txt
logilab_sphinx_themes.egg-info/top_level.txt
logilab_sphinx_themes/static/contents.png
logilab_sphinx_themes/static/lglb-sphinx-doc.css
logilab_sphinx_themes/static/logilab_logo.png
logilab_sphinx_themes/static/logilab_logo.svg
logilab_sphinx_themes/static/navigation.png